click_prompt/__init__.py
click_prompt/core/__init__.py
click_prompt/core/argument.py
click_prompt/core/option.py
click_prompt/core/parameter.py
click_prompt/decorators/__init__.py
click_prompt/decorators/argument.py
click_prompt/decorators/option.py
click_prompt-0.7.1.dist-info/WHEEL
click_prompt-0.7.1.dist-info/METADATA
click_prompt-0.7.1.dist-info/RECORD
