Metadata-Version: 2.3
Name: click-prompt
Version: 0.7.1
Summary: click-prompt provides more beautiful interactive options for the Python click library
Keywords: cli
Author: Markus Grotz
Author-email: Markus Grotz <grotz@uw.edu>
License: MIT License
Classifier: Programming Language :: Python :: 3
Classifier: Programming Language :: Python :: 3.9
Classifier: Programming Language :: Python :: 3.10
Classifier: Programming Language :: Python :: 3.11
Classifier: Programming Language :: Python :: 3.12
Classifier: Programming Language :: Python :: 3.13
Classifier: Programming Language :: Python :: 3.14
Classifier: License :: OSI Approved :: MIT License
Classifier: Operating System :: OS Independent
Classifier: Intended Audience :: Developers
Classifier: Environment :: Console
Requires-Dist: click>=8.0.4
Requires-Dist: questionary>=1.10.0
Requires-Dist: pytest ; extra == 'dev'
Requires-Dist: toml ; extra == 'dev'
Requires-Dist: myst-parser ; extra == 'dev'
Requires-Dist: sphinx-rtd-theme ; extra == 'dev'
Requires-Dist: ruff ; extra == 'dev'
Requires-Python: >=3.9
Project-URL: documentation, https://github.com/markusgrotz/click-prompt
Project-URL: homepage, https://github.com/markusgrotz/click-prompt
Project-URL: repository, https://github.com/markusgrotz/click-prompt
Project-URL: tracker, https://github.com/markusgrotz/click-prompt/issues
Provides-Extra: dev
